{
	"info": {
		"_postman_id": "ca322f34-b6ea-48de-8612-0047948ec74c",
		"name": "ASDN",
		"schema": "https://schema.getpostman.com/json/collection/v2.1.0/collection.json"
	},
	"item": [
		{
			"name": "Single Customer",
			"request": {
				"method": "GET",
				"header": [
					{
						"key": "",
						"value": "",
						"type": "default"
					}
				],
				"url": {
					"raw": "{{url}}/api/v1/customers/1",
					"host": [
						"{{url}}"
					],
					"path": [
						"api",
						"v1",
						"customers",
						"1"
					]
				}
			},
			"response": []
		},
		{
			"name": "Main",
			"request": {
				"method": "GET",
				"header": [
					{
						"key": "",
						"value": "",
						"type": "default"
					}
				],
				"url": {
					"raw": "{{url}}",
					"host": [
						"{{url}}"
					]
				}
			},
			"response": []
		},
		{
			"name": "Listing test",
			"protocolProfileBehavior": {
				"disableBodyPruning": true
			},
			"request": {
				"method": "GET",
				"header": [
					{
						"key": "Content-Type",
						"value": "application/json",
						"type": "default",
						"disabled": true
					},
					{
						"key": "",
						"value": "",
						"type": "default"
					}
				],
				"body": {
					"mode": "raw",
					"raw": ""
				},
				"url": {
					"raw": "http://localhost:8080/bla/1?name=Tim",
					"protocol": "http",
					"host": [
						"localhost"
					],
					"port": "8080",
					"path": [
						"bla",
						"1"
					],
					"query": [
						{
							"key": "name",
							"value": "Tim"
						}
					]
				}
			},
			"response": []
		},
		{
			"name": "Customers",
			"request": {
				"method": "GET",
				"header": [
					{
						"key": "",
						"value": "",
						"type": "default"
					}
				],
				"url": {
					"raw": "{{url}}/api/v1/customers",
					"host": [
						"{{url}}"
					],
					"path": [
						"api",
						"v1",
						"customers"
					]
				}
			},
			"response": []
		},
		{
			"name": "Module 2",
			"request": {
				"method": "GET",
				"header": [],
				"url": {
					"raw": "http://localhost:8080/module2?sort=ascaf",
					"protocol": "http",
					"host": [
						"localhost"
					],
					"port": "8080",
					"path": [
						"module2"
					],
					"query": [
						{
							"key": "sort",
							"value": "ascaf"
						}
					]
				}
			},
			"response": []
		},
		{
			"name": "Post Customer",
			"request": {
				"method": "POST",
				"header": [
					{
						"warning": "This is a duplicate header and will be overridden by the Content-Type header generated by Postman.",
						"key": "Content-Type",
						"value": "application/json",
						"type": "default"
					}
				],
				"body": {
					"mode": "raw",
					"raw": "{\n    \"id\": 11,\n    \"firstName\": \"Tim\"\n}",
					"options": {
						"raw": {
							"language": "json"
						}
					}
				},
				"url": {
					"raw": "http://localhost:8080/api/v1/customers",
					"protocol": "http",
					"host": [
						"localhost"
					],
					"port": "8080",
					"path": [
						"api",
						"v1",
						"customers"
					]
				}
			},
			"response": []
		},
		{
			"name": "Post Customer",
			"request": {
				"method": "POST",
				"header": [
					{
						"warning": "This is a duplicate header and will be overridden by the Content-Type header generated by Postman.",
						"key": "Content-Type",
						"value": "application/json",
						"type": "default"
					}
				],
				"body": {
					"mode": "raw",
					"raw": "{\n    \"firstName\": \"Sjaakjsasdffe\"\n}",
					"options": {
						"raw": {
							"language": "json"
						}
					}
				},
				"url": {
					"raw": "{{url}}api/v1/customers",
					"host": [
						"{{url}}api"
					],
					"path": [
						"v1",
						"customers"
					]
				}
			},
			"response": []
		}
	]
}